AUTHORS
LICENSE
MANIFEST.in
README.md
pyproject.toml
setup.cfg
setup.py
doc/Makefile
doc/README.md
doc/__init__.py
doc/autobuild.py
doc/doc-requirements.txt
doc/sources/changelog.rst
doc/sources/conf.py
doc/sources/contact.rst
doc/sources/contents.rst.inc
doc/sources/contribute.rst
doc/sources/faq.rst
doc/sources/guide-index.rst
doc/sources/index.rst
doc/sources/kivy-logo.png
doc/sources/kivystyle.sty
doc/sources/logo.png
doc/sources/migration.rst
doc/sources/philosophy.rst
doc/sources/tutorials-index.rst
doc/sources/user-guide.rst
doc/sources/.static/disclosure_down.png
doc/sources/.static/disclosure_up.png
doc/sources/.static/element-class-16.png
doc/sources/.static/element-enumeration-16.png
doc/sources/.static/element-field-16.png
doc/sources/.static/element-method-16.png
doc/sources/.static/element-property-16.png
doc/sources/.static/element-structure-16.png
doc/sources/.static/fresh.css
doc/sources/.static/jquery-effects-core-and-slide.js
doc/sources/.static/jquery.cookie.js
doc/sources/.static/kivy.js
doc/sources/.static/logo-kivy.png
doc/sources/.templates/layout.html
doc/sources/examples/README
doc/sources/gettingstarted/diving.rst
doc/sources/gettingstarted/drawing.rst
doc/sources/gettingstarted/events.rst
doc/sources/gettingstarted/first_app.rst
doc/sources/gettingstarted/framework.rst
doc/sources/gettingstarted/index.rst
doc/sources/gettingstarted/installation.rst
doc/sources/gettingstarted/intro.rst
doc/sources/gettingstarted/layouts.rst
doc/sources/gettingstarted/packaging.rst
doc/sources/gettingstarted/properties.rst
doc/sources/gettingstarted/rules.rst
doc/sources/guide/android.rst
doc/sources/guide/architecture.rst
doc/sources/guide/basic.rst
doc/sources/guide/config.rst
doc/sources/guide/environment.rst
doc/sources/guide/events.rst
doc/sources/guide/graphics.rst
doc/sources/guide/inputs.rst
doc/sources/guide/lang.rst
doc/sources/guide/licensing.rst
doc/sources/guide/other-frameworks.rst
doc/sources/guide/packaging-android.rst
protonox_kivy.egg-info/PKG-INFO
protonox_kivy.egg-info/SOURCES.txt
protonox_kivy.egg-info/dependency_links.txt
protonox_kivy.egg-info/top_level.txt