Metadata-Version: 2.4
Name: protonox-kivy
Version: 3.0.0.dev13
Summary: Protonox-maintained fork of Kivy intended as a drop-in compatible build for Protonox tooling and deployments
Home-page: https://github.com/ProtonoxDEV/Protonox-Kivy-Multiplatform-Framework
Author: ProtonoxDEV (fork maintainers)
Author-email: "ProtonoxDEV (fork maintainers)" <contact@protonox.dev>
License: MIT
Project-URL: Homepage, https://github.com/ProtonoxDEV/Protonox-Kivy-Multiplatform-Framework
Project-URL: Documentation, https://github.com/ProtonoxDEV/Protonox-Kivy-Multiplatform-Framework/tree/codex/normalize-and-clean-repository-structure/kivy-protonox-version/doc
Project-URL: Repository, https://github.com/ProtonoxDEV/Protonox-Kivy-Multiplatform-Framework
Project-URL: Bug Reports, https://github.com/ProtonoxDEV/Protonox-Kivy-Multiplatform-Framework/issues
Project-URL: Upstream Kivy, https://github.com/kivy/kivy
Keywords: kivy,android,buildozer,python-for-android,pyjnius
Classifier: Development Status :: 4 - Beta
Classifier: Environment :: MacOS X
Classifier: Environment :: Win32 (MS Windows)
Classifier: Environment :: X11 Applications
Classifier: Intended Audience :: Developers
Classifier: Intended Audience :: End Users/Desktop
Classifier: Intended Audience :: Information Technology
Classifier: Intended Audience :: Science/Research
Classifier: License :: OSI Approved :: MIT License
Classifier: Natural Language :: English
Classifier: Operating System :: MacOS :: MacOS X
Classifier: Operating System :: Microsoft :: Windows
Classifier: Operating System :: POSIX :: BSD :: FreeBSD
Classifier: Operating System :: POSIX :: Linux
Classifier: Programming Language :: Python :: 3.9
Classifier: Programming Language :: Python :: 3.10
Classifier: Programming Language :: Python :: 3.11
Classifier: Programming Language :: Python :: 3.12
Classifier: Programming Language :: Python :: 3.13
Classifier: Programming Language :: Python :: 3.14
Classifier: Topic :: Artistic Software
Classifier: Topic :: Games/Entertainment
Classifier: Topic :: Multimedia :: Graphics :: 3D Rendering
Classifier: Topic :: Multimedia :: Graphics :: Capture :: Digital Camera
Classifier: Topic :: Multimedia :: Graphics :: Presentation
Classifier: Topic :: Multimedia :: Graphics :: Viewers
Classifier: Topic :: Multimedia :: Sound/Audio :: Players :: MP3
Classifier: Topic :: Multimedia :: Video :: Display
Classifier: Topic :: Scientific/Engineering :: Human Machine Interfaces
Classifier: Topic :: Scientific/Engineering :: Visualization
Classifier: Topic :: Software Development :: Libraries :: Application Frameworks
Classifier: Topic :: Software Development :: User Interfaces
Requires-Python: >=3.9
License-File: LICENSE
License-File: AUTHORS
Dynamic: author
Dynamic: home-page
Dynamic: license-file
